tutorrichiesitefactory/__about__.py
tutorrichiesitefactory/__init__.py
tutorrichiesitefactory/plugin.py
tutorrichiesitefactory/patches/kustomization
tutorrichiesitefactory/patches/openedx-auth
tutorrichiesitefactory/patches/openedx-cms-production-settings
tutorrichiesitefactory/patches/openedx-common-settings
tutorrichiesitefactory/patches/openedx-development-settings
tutorrichiesitefactory/patches/openedx-dockerfile-post-python-requirements
tutorrichiesitefactory/patches/openedx-lms-production-settings
tutorrichiesitefactory/patches_per_site/caddyfile
tutorrichiesitefactory/patches_per_site/caddyfile-lms
tutorrichiesitefactory/patches_per_site/k8s-deployments
tutorrichiesitefactory/patches_per_site/k8s-jobs
tutorrichiesitefactory/patches_per_site/k8s-services
tutorrichiesitefactory/patches_per_site/local-docker-compose-dev-services
tutorrichiesitefactory/patches_per_site/local-docker-compose-jobs-services
tutorrichiesitefactory/patches_per_site/local-docker-compose-services
tutorrichiesitefactory/patches_per_site/openedx-lms-development-settings
tutorrichiesitefactory/patches_per_site/openedx-lms-production-settings
tutorrichiesitefactory/patches_per_site/richie-kubernetes-secret-generator
tutorrichiesitefactory/patches_per_site/richie-openedx-sync-course-hooks
tutorrichiesitefactory/templates/richie/apps/env.d/development
tutorrichiesitefactory/templates/richie/apps/env.d/production
tutorrichiesitefactory/templates/richie/tasks/lms/init
tutorrichiesitefactory/templates/richie/tasks/mysql/init
tutorrichiesitefactory/templates/richie/tasks/richie/init
tutor_contrib_richie_site_factory-20.0.1.dist-info/METADATA
tutor_contrib_richie_site_factory-20.0.1.dist-info/WHEEL
tutor_contrib_richie_site_factory-20.0.1.dist-info/entry_points.txt
tutor_contrib_richie_site_factory-20.0.1.dist-info/top_level.txt
tutor_contrib_richie_site_factory-20.0.1.dist-info/RECORD
