Metadata-Version: 2.4
Name: tutor-contrib-richie-site-factory
Version: 20.0.1
Summary: Richie site factory plugin for Tutor
Home-page: https://github.com/fccn/tutor-contrib-richie-site-factory
Author: FCCN
License: AGPLv3
Project-URL: Code, https://github.com/fccn/tutor-contrib-richie-site-factory
Project-URL: Issue tracker, https://github.com/fccn/tutor-contrib-richie-site-factory/issues
Classifier: Development Status :: 5 - Production/Stable
Classifier: Intended Audience :: Developers
Classifier: License :: OSI Approved :: GNU Affero General Public License v3
Classifier: Operating System :: OS Independent
Classifier: Programming Language :: Python
Classifier: Programming Language :: Python :: 3.10
Classifier: Programming Language :: Python :: 3.11
Classifier: Programming Language :: Python :: 3.12
Requires-Python: >=3.7
Requires-Dist: tutor<21.0.0,>=20.0.0
Dynamic: author
Dynamic: classifier
Dynamic: description
Dynamic: description-content-type
Dynamic: home-page
Dynamic: license
Dynamic: project-url
Dynamic: requires-dist
Dynamic: requires-python
Dynamic: summary
